utils4/__init__.py
utils4/_version.py
utils4/changelog.py
utils4/cmaps.py
utils4/config.py
utils4/convert.py
utils4/crypto.py
utils4/cutils.py
utils4/dfdiff.py
utils4/dict2obj.py
utils4/filesys.py
utils4/futils.pyd
utils4/futilsmodule.c
utils4/log.py
utils4/mathfunc.pyd
utils4/mathfuncmodule.c
utils4/palette.py
utils4/progressbar.py
utils4/pywarnings.py
utils4/reader.py
utils4/registry.py
utils4/reporterror.py
utils4/srccheck.py
utils4/stats.py
utils4/termcolour.py
utils4/tickers.py
utils4/timedelta.py
utils4/user_interface.py
utils4/utils.py
utils4/validation.py
utils4/libs/Makefile
utils4/libs/_futils.c
utils4/libs/_futils.h
utils4/libs/_mathfunc.c
utils4/libs/_mathfunc.h
utils4-1.8.1.dist-info/LICENSE
utils4-1.8.1.dist-info/METADATA
utils4-1.8.1.dist-info/WHEEL
utils4-1.8.1.dist-info/top_level.txt
utils4-1.8.1.dist-info/RECORD
